README.md
setup.cfg
setup.py
Monopoly/Monopoly.py
Monopoly/__init__.py
Monopoly/../README.md
Monopopy.egg-info/PKG-INFO
Monopopy.egg-info/SOURCES.txt
Monopopy.egg-info/dependency_links.txt
Monopopy.egg-info/requires.txt
Monopopy.egg-info/top_level.txt