Metadata-Version: 1.0
Name: Monopopy
Version: 0.1a1
Summary: Monopoly clone using PyGame by Ryan J. Slater
Home-page: https://github.com/rjslater2000/Monopoly
Author: Ryan J. Slater
Author-email: ryan.j.slater.2@gmail.com
License: UNKNOWN
Keywords: Monopoly
Platform: UNKNOWN
